<?xml version="1.0" encoding="UTF-8"?>
<GUI w="990" h="38" backgroundColor="#00000000">
<!-- if we do this, then hikey rect end MUST lte start of circle for 1 and 8   -->
	<CS01ViewContainer1 x="0" y="0" w="990" h="38" disabled_x="55" disabled_y="0" disabled_w="925" disabled_h="38" style="ChannelsViewContainer1" >
		<StaticText text="$OP_NUM" x="10" y="10" w="10" h="16" font="SFCHEADING_16"/>

		<CS01OnOffButton style="SPCOnOff" param="512" x="28" y="9" role="onOff"/>
		<!--Rect               x="55" y="0" w="105" h="40" drawMode="filled" fill_color="#54585aFF" -->

		<CS01OptionMenuPool x="55" y="0" w="115" h="40" font="SFC_11" text_x="5" text_y="3" text_w="105" text_h="30"
							style="OptionMenuPool" 						    param="773" target="com.Plogue.Emulator.SFC|0|7E87|2" vmin="0" vmax="16" vdefault="0" enabledByOnOff="1"
							mod_font="SFC_8" modText_x="10" modText_y="25" modText_w="95" modText_h="9"
						    >
			<CS01OptionItem type="added" name="None" value="16"/>
			<CS01OptionItem type="pool"  valueStart="0" valueEnd="15" nameEmpty="Nothing loaded" valueDisplayFormat="%c" valueDisplayOffset="65"/>
		</CS01OptionMenuPool> 

		<CS03Knob style="SPCKnob3" param="768" x="180" y="3" vmin="0" vmax="15" vdefault="0"  stepped="1" mouseIncrement="0.08" enabledByOnOff="1"/>
		<CS03Knob style="SPCKnob3" param="769" x="222" y="3" vmin="0" vmax="7"  vdefault="7"  stepped="1" mouseIncrement="0.04" enabledByOnOff="1"/>
		<CS03Knob style="SPCKnob3" param="770" x="264" y="3" vmin="0" vmax="7"  vdefault="7"  stepped="1" mouseIncrement="0.04" enabledByOnOff="1"/>
		<CS03Knob style="SPCKnob3" param="771" x="306" y="3" vmin="0" vmax="31" vdefault="31" stepped="1" mouseIncrement="0.16" enabledByOnOff="1"/>
		<CS03Knob style="SPCKnob3" param="772" x="348" y="3" vmin="0" vmax="32" vdefault="0"  stepped="1" mouseIncrement="0.16" enabledByOnOff="1"/>

		<!-- Noise FM Echo Inv Surnd -->
		<CS01OnOffButton style="SPCOnOff" param="774" x="403" y="9" enabledByOnOff="1"/>
		<CS01OnOffButton style="SPCOnOff" param="775" x="433" y="$FM_BTN_POS" enabledByOnOff="1"/>
		<CS01OnOffButton style="SPCOnOff" param="777" x="463" y="9" enabledByOnOff="1"/>
		<CS01OnOffButton style="SPCOnOff" param="778" x="493" y="9" enabledByOnOff="1"/>
		<CS01OnOffButton style="SPCOnOff" param="779" x="523" y="9" enabledByOnOff="1"/>

		<!-- Retrig -->
		<VisibilityContainer x="558" y="0" w="20" h="38" enabledByOnOff="1">
			<CS03Knob param="DID_SLOTPOLY" x="0" y="0" w="0" h="0" role="controller" controller_name="POLY_COUNT"/>
			<CS01OnOffButton style="SPCOnOff" param="513" x="0" y="9" rule="eq" controller="POLY_COUNT" rule_d1="1"/>
		</VisibilityContainer>

		<!-- delay -->
		<CS03Knob style="SPCKnob3" param="516" x="600" y="3" vmin="0" vmax="99" vdefault="0" stepped="1" mouseIncrement="0.5" enabledByOnOff="1"/>

		<!-- Fixed -->
		<CS01OnOffButton style="SPCOnOff" param="520" x="653" y="9" enabledByOnOff="1"/>

		<!-- Coarse, Fine, Vol, Pan Glide-->
		<CS03Knob style="SPCKnob3" param="517" x="692" y="3" vmin="-128" vmax="128" vdefault="0" stepped="1" unipolar="0" mouseIncrement="0.25" enabledByOnOff="1"/>
		<CS03Knob style="SPCKnob3" param="518" x="734" y="3" vmin="-100" vmax="100" vdefault="0" stepped="1" unipolar="0"                       enabledByOnOff="1"/>
		<CS03Knob style="SPCKnob3" param="519" x="776" y="3" vmin="0"    vmax="1"   vdefault="1"                                                enabledByOnOff="1"/>
		<CS03Knob style="SPCKnob3" param="776" x="818" y="3" vmin="-128" vmax="128" vdefault="0" stepped="1" unipolar="0"                       enabledByOnOff="1"/>
		<CS03Knob style="SPCKnob3" param="523" x="860" y="3" vmin="0"    vmax="100" vdefault="0" stepped="1"              mouseIncrement="0.5"  enabledByOnOff="1"/>

		<!--lokey-->
<!--		<Rect     x="902" y="07" w="30" h="23" border_color="#000000FF" drawMode="stroked" frameWidth="1"/> -->
		<CS01Knob x="902" style="SPClohi" param="514" vdefault="0" mouseIncrement="0.5" enabledByOnOff="1">
			<XMLMacroTextUse name="optionMenuKnoblohi"/>
		</CS01Knob>

		<!--hikey-->
<!--		<Rect     x="944" y="007" w="30" h="23" border_color="#000000FF" drawMode="stroked" frameWidth="1"/> -->
		<CS01Knob x="944" style="SPClohi" param="515" vdefault="127" mouseIncrement="0.5" enabledByOnOff="1">
			<XMLMacroTextUse name="optionMenuKnoblohi"/>
		</CS01Knob>

	</CS01ViewContainer1>
</GUI>
